LICENSE
MANIFEST.in
setup.cfg
setup.py
pyharness/__init__.py
pyharness/command_line.py
pyharness/experiment.py
pyharness/param.py
pyharness/stat_loader.py
pyharness/stat_logger.py
pyharness.egg-info/PKG-INFO
pyharness.egg-info/SOURCES.txt
pyharness.egg-info/dependency_links.txt
pyharness.egg-info/entry_points.txt
pyharness.egg-info/top_level.txt