Metadata-Version: 1.1
Name: pyharness
Version: 0.1.2
Summary: A lightweight framework for running experiments
Home-page: https://github.com/thisisdhaas/pyharness
Author: Daniel Haas
Author-email: thisisdhaas@gmail.com
License: UNKNOWN
Download-URL: https://github.com/thisisdhaas/pyharness/tarball/v0.1.2
Keywords: experiments,harness
Platform: UNKNOWN
